aury/__init__.py
aury/sdk/__init__.py
aury/sdk/storage/__init__.py
aury/sdk/storage/exceptions.py
aury/sdk/storage/py.typed
aury/sdk/storage/storage/__init__.py
aury/sdk/storage/storage/base.py
aury/sdk/storage/storage/cos.py
aury/sdk/storage/storage/factory.py
aury/sdk/storage/storage/models.py
aury/sdk/storage/storage/s3.py
aury/sdk/storage/sts/__init__.py
aury/sdk/storage/sts/factory.py
aury/sdk/storage/sts/models.py
aury/sdk/storage/sts/policy.py
aury/sdk/storage/sts/provider.py
aury/sdk/storage/sts/providers/__init__.py
aury/sdk/storage/sts/providers/tencent.py
aury_sdk_storage-0.0.9.dist-info/METADATA
aury_sdk_storage-0.0.9.dist-info/WHEEL
aury_sdk_storage-0.0.9.dist-info/RECORD
