Metadata-Version: 2.4
Name: aury-sdk-storage
Version: 0.0.9
Summary: Multi-cloud storage SDK with STS support (AWS, Aliyun OSS, Tencent COS)
Requires-Python: >=3.13
Requires-Dist: httpx>=0.27
Requires-Dist: pydantic>=2.0
Provides-Extra: aws
Requires-Dist: aioboto3>=13.0; extra == 'aws'
Provides-Extra: cos
Requires-Dist: cos-python-sdk-v5>=1.9.0; extra == 'cos'
Provides-Extra: dev
Requires-Dist: pytest-asyncio>=0.24; extra == 'dev'
Requires-Dist: pytest>=8.0; extra == 'dev'
